cmdmock/__init__.py
cmdmock-1.1.0.dist-info/METADATA
cmdmock-1.1.0.dist-info/WHEEL
cmdmock-1.1.0.dist-info/entry_points.txt
cmdmock-1.1.0.dist-info/licenses/LICENSE.txt
cmdmock-1.1.0.dist-info/RECORD
