Metadata-Version: 2.4
Name: cmdmock
Version: 1.1.0
Summary: a simplistic mocking framework for CLI commands
License-Expression: MIT
License-File: LICENSE.txt
Keywords: command,mock
Author: Pierre Smeyers
Author-email: pierre.smeyers@gmail.com
Requires-Python: >=3.8
Classifier: Development Status :: 4 - Beta
Classifier: Environment :: Console
Classifier: Intended Audience :: Developers
Classifier: License :: OSI Approved :: MIT License
Classifier: Operating System :: OS Independent
Classifier: Programming Language :: Python
Classifier: Programming Language :: Python :: 3
Classifier: Programming Language :: Python :: 3.8
Classifier: Programming Language :: Python :: 3.9
Classifier: Programming Language :: Python :: 3.10
Classifier: Programming Language :: Python :: 3.11
Classifier: Programming Language :: Python :: 3.12
Classifier: Programming Language :: Python :: 3 :: Only
Classifier: Topic :: Software Development :: Testing :: Mocking
Classifier: Topic :: System :: Shells
Project-URL: Homepage, https://github.com/pismy/cmdmock
Project-URL: Issues, https://github.com/pismy/cmdmock/issues
